<?xml version="1.0" encoding="us-ascii" standalone="no"?>
<!DOCTYPE TimeML SYSTEM "../../dtd/ISO-TimeML-Ro.dtd">
<TimeML xmlns:xsi="http://www.w3.org/2001/XMLSchema-instance" xsi:noNamespaceSchemaLocation="../../dtd/timeml_1.2.1.xsd">
  <DOCNO> WSJ891027-0150 </DOCNO>
  <DD> = 891027 </DD>
  <AN> 891027-0150. </AN>
  <HL> GM Seeks to Buy Up to 15% of Jaguar,
@  Heating Up Its Skirmishing With Ford
@  ----
@  By Joann S. Lublin
@  Staff Reporter of The Wall Street Journal </HL>
  <DD> <TIMEX3 functionInDocument="CREATION_TIME" temporalFunction="false" tid="t157" type="DATE" value="1989-10-27">10/27/89</TIMEX3> </DD>
  <SO> WALL STREET JOURNAL (J) </SO>
  <CO> GM JAGRY F EUROP </CO>
  <IN> TENDER OFFERS, MERGERS, ACQUISITIONS (TNM)
AUTOMOBILES (AUT) </IN>
  <DATELINE> LONDON  </DATELINE>
  <TEXT>
    <s><ENAMEX TYPE="ORGANIZATION">General Motors Corp .</ENAMEX><EVENT aspect="NONE" class="I_STATE" eid="e1" eiid="ei2451" eventID="e1" polarity="POS" pos="VERB" tense="PRESENT">vrea</EVENT>s&abreve;<EVENT aspect="NONE" class="OCCURRENCE" eid="e3" eiid="ei2452" eventID="e3" polarity="POS" pos="VERB" tense="INFINITIVE">cumpere</EVENT>p&acirc;n&abreve;_la<NUMEX TYPE="PERCENT">15%</NUMEX>din<ENAMEX TYPE="ORGANIZATION">Jaguar PLC</ENAMEX>,<EVENT aspect="NONE" class="OCCURRENCE" eid="e4" eiid="ei2453" eventID="e4" polarity="POS" pos="VERB" tense="PRESPART">marc&acirc;ndu</EVENT>-&scedil;i prima<EVENT aspect="NONE" class="OCCURRENCE" eid="e5" eiid="ei2454" eventID="e5" polarity="POS" pos="NOUN" tense="NONE">salv&abreve;</EVENT>dintr- o posibil&abreve;<EVENT aspect="NONE" class="OCCURRENCE" eid="e6" eiid="ei2455" eventID="e6" polarity="POS" pos="NOUN" tense="NONE">b&abreve;t&abreve;lie</EVENT>la scar&abreve; mare &icirc;mpotriva<ENAMEX TYPE="ORGANIZATION">Ford Motor Co.</ENAMEX>pentru<EVENT aspect="NONE" class="STATE" eid="e147" eiid="ei2456" eventID="e147" polarity="POS" pos="NOUN" tense="NONE">controlul</EVENT>fabricantului de ma&scedil;ini britanic .</s>
    <s><ENAMEX TYPE="ORGANIZATION">GM</ENAMEX>a <EVENT aspect="NONE" class="I_ACTION" eid="e8" eiid="ei2457" eventID="e8" polarity="POS" pos="VERB" tense="PAST">urm&abreve;rit</EVENT><EVENT aspect="NONE" class="I_STATE" eid="e159" eiid="ei2458" eventID="e159" polarity="POS" pos="NOUN" tense="NONE">aprobarea</EVENT>antimonopolului american<TIMEX3 anchorTimeID="t157" functionInDocument="NONE" temporalFunction="true" tid="t158" type="DATE" value="1989-W42">s&abreve;pt&abreve;m&acirc;na trecut&abreve;</TIMEX3>ca s&abreve;<EVENT aspect="NONE" class="OCCURRENCE" eid="e10" eiid="ei2459" eventID="e10" polarity="POS" pos="VERB" tense="INFINITIVE">achizi&tcedil;ioneze</EVENT>ac&tcedil;iuni<ENAMEX TYPE="ORGANIZATION">Jaguar</ENAMEX>&icirc;n valoare de mai mult de<NUMEX TYPE="MONEY">$ 15 milioane</NUMEX>dar nu<EVENT aspect="NONE" class="STATE" eid="e11" eiid="ei2460" eventID="e11" polarity="NEG" pos="VERB" tense="PRESENT">de&tcedil;ine</EVENT>nimic<TIMEX3 anchorTimeID="t157" functionInDocument="NONE" temporalFunction="true" tid="t161" type="DATE" value="PRESENT_REF">&icirc;nc&abreve;</TIMEX3>,<EVENT aspect="NONE" class="REPORTING" eid="e149" eiid="ei2461" eventID="e149" polarity="POS" pos="PREPOSITION" tense="PRESPART">potrivit</EVENT>oficialilor GM de aici &scedil;i de_la sediul<ENAMEX TYPE="LOCATION">din Detroit</ENAMEX>al companiei .</s>
    <s>Fabricantul nr. 1 de ma&scedil;ini<ENAMEX TYPE="LOCATION">american</ENAMEX> a<EVENT aspect="NONE" class="REPORTING" eid="e13" eiid="ei2462" eventID="e13" polarity="POS" pos="VERB" tense="PAST">scris</EVENT>apoi<ENAMEX TYPE="ORGANIZATION">Jaguar</ENAMEX>c&abreve;<EVENT aspect="NONE" class="I_STATE" eid="e14" eiid="ei2463" eventID="e14" polarity="POS" pos="VERB" tense="PRESENT">inten&tcedil;ioneaz&abreve;</EVENT>" s&abreve;<EVENT aspect="NONE" class="OCCURRENCE" eid="e16" eiid="ei2464" eventID="e16" polarity="POS" pos="VERB" tense="PRESENT">ajung&abreve;</EVENT>la acel<EVENT aspect="NONE" class="STATE" eid="e150" eiid="ei2465" eventID="e150" polarity="POS" pos="OTHER" tense="NONE">nivel<NUMEX TYPE="PERCENT">de 15%</NUMEX>"</EVENT><SIGNAL sid="s151">odat&abreve;_ce</SIGNAL><EVENT aspect="NONE" class="OCCURRENCE" eid="e17" eiid="ei2466" eventID="e17" polarity="POS" pos="VERB" tense="PRESENT">ob&tcedil;ine</EVENT><EVENT aspect="NONE" class="I_STATE" eid="e152" eiid="ei2467" eventID="e152" polarity="POS" pos="NOUN" tense="NONE">aprobarea</EVENT>SUA s&abreve;<EVENT aspect="NONE" class="OCCURRENCE" eid="e19" eiid="ei2468" eventID="e19" polarity="POS" pos="VERB" tense="INFINITIVE">mearg&abreve;</EVENT>dincolo_de<NUMEX TYPE="MONEY">$ 15 miliarde</NUMEX>, a<EVENT aspect="NONE" class="REPORTING" eid="e20" eiid="ei2470" eventID="e20" polarity="POS" pos="VERB" tense="PAST">spus</EVENT><TIMEX3 anchorTimeID="t157" functionInDocument="NONE" temporalFunction="true" tid="t163" type="DATE" value="1989-10-26">ieri</TIMEX3>un purt&abreve;tor de cuv&acirc;nt<ENAMEX TYPE="ORGANIZATION">de_la Jaguar</ENAMEX>.</s>
    <s><EVENT aspect="NONE" class="OCCURRENCE" eid="e154" eiid="ei2471" eventID="e154" polarity="POS" pos="NOUN" tense="NONE">Manevra</EVENT><ENAMEX TYPE="ORGANIZATION">GM</ENAMEX><SIGNAL sid="s155">urmeaz&abreve;</SIGNAL><EVENT aspect="NONE" class="REPORTING" eid="e22" eiid="ei2472" eventID="e22" polarity="POS" pos="NOUN" tense="NONE">declara&tcedil;ia</EVENT>de<TIMEX3 anchorTimeID="t157" functionInDocument="NONE" temporalFunction="true" tid="t164" type="DATE" value="1989-10-24">joi</TIMEX3>de_c&abreve;tre<ENAMEX TYPE="ORGANIZATION">Ford</ENAMEX>, care de&tcedil;ine o cot&abreve; nebinevenit&abreve;<NUMEX TYPE="PERCENT">de 12 . 45%</NUMEX>la<ENAMEX TYPE="ORGANIZATION">Jaguar</ENAMEX>, c&abreve; este<EVENT aspect="NONE" class="I_STATE" eid="e25" eiid="ei2473" eventID="e25" polarity="POS" pos="VERB" tense="PRESENT">preg&abreve;tit</EVENT>s&abreve;<EVENT aspect="NONE" class="OCCURRENCE" eid="e27" eiid="ei2474" eventID="e27" polarity="POS" pos="VERB" tense="INFINITIVE">liciteze</EVENT>pentru &icirc;ntreaga companie .</s>
    <s><ENAMEX TYPE="ORGANIZATION">GM</ENAMEX>este aproape de<EVENT aspect="NONE" class="ASPECTUAL" eid="e29" eiid="ei2475" eventID="e29" modality="close" polarity="POS" pos="VERB" tense="NONE">a &icirc;ncheia</EVENT>o<EVENT aspect="NONE" class="OCCURRENCE" eid="e30" eiid="ei2476" eventID="e30" polarity="POS" pos="NOUN" tense="NONE">&icirc;n&tcedil;elegere</EVENT>amiabil&abreve; cu<ENAMEX TYPE="ORGANIZATION">Jaguar</ENAMEX>care ar putea<EVENT aspect="NONE" class="I_STATE" eid="e2073" eiid="ei2477" eventID="e2073" modality="none" polarity="POS" pos="VERB" tense="INFINITIVE">implica</EVENT>o cot&abreve; eventual&abreve;<NUMEX TYPE="PERCENT">de 30%</NUMEX>&scedil;i<EVENT aspect="NONE" class="OCCURRENCE" eid="e2075" eiid="ei2478" eventID="e2075" polarity="POS" pos="NOUN" tense="NONE">societ&abreve;&tcedil;i</EVENT>mixte de produc&tcedil;ie .</s>
    <s>Investitorii speculativi ,<EVENT aspect="NONE" class="OCCURRENCE" eid="e35" eiid="ei2479" eventID="e35" polarity="POS" pos="VERB" tense="PRESPART">cont&acirc;nd</EVENT>pe o<EVENT aspect="NONE" class="OCCURRENCE" eid="e36" eiid="ei2480" eventID="e36" polarity="POS" pos="NOUN" tense="NONE">ciocnire</EVENT>iminent&abreve;<ENAMEX TYPE="ORGANIZATION">&icirc;ntre Ford</ENAMEX>&scedil;i<ENAMEX TYPE="ORGANIZATION">GM</ENAMEX>,<EVENT aspect="NONE" class="OCCURRENCE" eid="e38" eiid="ei2481" eventID="e38" polarity="POS" pos="VERB" tense="PAST">au m&abreve;rit</EVENT><TIMEX3 anchorTimeID="t157" functionInDocument="NONE" temporalFunction="true" tid="t313" type="DATE" value="1989-10-26">ieri</TIMEX3>pre&tcedil;ul ac&tcedil;iunilor<ENAMEX TYPE="ORGANIZATION">Jaguar</ENAMEX>cu<NUMEX TYPE="MONEY">cinci pence</NUMEX>(<NUMEX TYPE="MONEY">opt cen&tcedil;i americani</NUMEX>) la aproape un record de<NUMEX TYPE="MONEY"><EVENT aspect="NONE" class="STATE" eid="e2386" eiid="ei2546" eventID="e2386" polarity="POS" pos="OTHER" tense="NONE">720</EVENT>pence</NUMEX>(<NUMEX TYPE="MONEY">$ 11 . 60</NUMEX>) &icirc;n<EVENT aspect="NONE" class="OCCURRENCE" eid="e39" eiid="ei2484" eventID="e39" polarity="POS" pos="NOUN" tense="NONE">tranzac&tcedil;iile</EVENT>t&acirc;rzii de_pe bursa de valori a<ENAMEX TYPE="LOCATION">Londrei</ENAMEX>.</s>
    <s>De<TIMEX3 anchorTimeID="t157" functionInDocument="NONE" temporalFunction="true" tid="t314" type="DATE" value="1989-10-24">joi</TIMEX3>, ac&tcedil;iunile au<EVENT aspect="PERFECTIVE" class="OCCURRENCE" eid="e42" eiid="ei2485" eventID="e42" polarity="POS" pos="VERB" tense="PRESENT">c&acirc;&scedil;tigat</EVENT>aproape<NUMEX TYPE="PERCENT">4%</NUMEX>.</s>
    <s>Dar un<EVENT aspect="NONE" class="OCCURRENCE" eid="e2091" eiid="ei2486" eventID="e2091" modality="unlikely" polarity="NEG" pos="NOUN" tense="NONE">r&abreve;zboi</EVENT>global al licit&abreve;rilor &icirc;ntre cei mai mari gigan&tcedil;i auto ai lumii pentru principalul fabricant de ma&scedil;ini de lux al<ENAMEX TYPE="LOCATION">Marii_Britanii</ENAMEX>pare improbabil .</s>
    <s>"Nu vom<EVENT aspect="NONE" class="OCCURRENCE" eid="e46" eiid="ei2487" eventID="e46" polarity="NEG" pos="VERB" tense="FUTURE">dep&abreve;&scedil;i</EVENT> un anumit nivel," a<EVENT aspect="NONE" class="REPORTING" eid="e48" eiid="ei2488" eventID="e48" polarity="POS" pos="VERB" tense="PAST">spus</EVENT> <ENAMEX TYPE="PERSON">David N. McCammon</ENAMEX>, vicepre&scedil;edintele financiar al <ENAMEX TYPE="ORGANIZATION">Ford</ENAMEX>, la o <EVENT aspect="NONE" class="OCCURRENCE" eid="e316" eiid="ei2489" eventID="e316" polarity="POS" pos="NOUN" tense="NONE">conferin&tcedil;&abreve;</EVENT> de pres&abreve; <TIMEX3 anchorTimeID="t157" functionInDocument="NONE" temporalFunction="true" tid="t315" type="DATE" value="1989-10-26">ieri</TIMEX3> &icirc;n <ENAMEX TYPE="LOCATION">Dearborn</ENAMEX>, <ENAMEX TYPE="LOCATION">Mich.</ENAMEX>
"Exist&abreve; un pretcedil; la care ne-am <EVENT aspect="NONE" class="ASPECTUAL" eid="e50" eiid="ei2490" eventID="e50" modality="'d" polarity="POS" pos="VERB" tense="NONE">opri</EVENT> din<EVENT aspect="NONE" class="OCCURRENCE" eid="e52" eiid="ei2491" eventID="e52" polarity="POS" pos="NOUN" tense="NONE">licitat</EVENT>."</s>
    <s>El nu a vrut s&abreve;<EVENT aspect="NONE" class="OCCURRENCE" eid="e53" eiid="ei2492" eventID="e53" modality="would" polarity="NEG" pos="VERB" tense="NONE">precizeze</EVENT>care era acesta .</s>
    <s>Iar<EVENT aspect="NONE" class="STATE" eid="e318" eiid="ei2493" eventID="e318" polarity="POS" pos="NOUN" tense="NONE">presiunile</EVENT>politice puternice ar putea<EVENT aspect="NONE" class="I_ACTION" eid="e56" eiid="ei2494" eventID="e56" modality="may" polarity="POS" pos="VERB" tense="NONE">convinge</EVENT>guvernul conservator s&abreve; -&scedil;i<EVENT aspect="NONE" class="OCCURRENCE" eid="e59" eiid="ei2495" eventID="e59" polarity="POS" pos="VERB" tense="INFINITIVE">p&abreve;streze</EVENT>a&scedil;a- numita cot&abreve; de aur , care limiteaz&abreve; orice proprietate individual&abreve; la<NUMEX TYPE="PERCENT">15%</NUMEX>,<SIGNAL sid="s62">p&acirc;n&abreve;_ce</SIGNAL><EVENT aspect="NONE" class="ASPECTUAL" eid="e63" eiid="ei2497" eventID="e63" polarity="POS" pos="VERB" tense="PRESENT">expir&abreve;</EVENT><EVENT aspect="NONE" class="OCCURRENCE" eid="e322" eiid="ei2496" eventID="e322" polarity="POS" pos="NOUN" tense="NONE">restric&tcedil;ia</EVENT><SIGNAL sid="s326">pe</SIGNAL><TIMEX3 functionInDocument="NONE" temporalFunction="false" tid="t325" type="DATE" value="1990-12-31">31_dec._1990</TIMEX3>.</s>
    <s>" Chiar nu<EVENT aspect="NONE" class="I_STATE" eid="e64" eiid="ei2498" eventID="e64" polarity="NEG" pos="VERB" tense="PRESENT">v&abreve;d</EVENT>guvernul<EVENT aspect="NONE" class="OCCURRENCE" eid="e66" eiid="ei2499" eventID="e66" polarity="POS" pos="VERB" tense="NONE">f&abreve;c&acirc;nd</EVENT>ceva ce<ENAMEX TYPE="ORGANIZATION">Jaguar</ENAMEX>nu<EVENT aspect="NONE" class="I_STATE" eid="e67" eiid="ei2500" eventID="e67" polarity="NEG" pos="VERB" tense="PRESENT">vrea</EVENT><SIGNAL sid="s328">&icirc;n</SIGNAL><TIMEX3 beginPoint="t157" functionInDocument="NONE" temporalFunction="true" tid="t327" type="DURATION" value="P14M">urm&abreve;toarele 14_luni</TIMEX3>, a "<EVENT aspect="NONE" class="REPORTING" eid="e69" eiid="ei2501" eventID="e69" polarity="POS" pos="VERB" tense="PAST">spus</EVENT><ENAMEX TYPE="PERSON">Kenneth Warren</ENAMEX>, un membru conservator al <ENAMEX TYPE="ORGANIZATION">Parlamentului</ENAMEX>&scedil;i pre&scedil;edinte al<ENAMEX TYPE="ORGANIZATION">Comitetului Ales pentru Comer&tcedil;</ENAMEX>&scedil;i<ENAMEX TYPE="LOCATION">Industrie</ENAMEX>&icirc;n<ENAMEX TYPE="ORGANIZATION">Camera Comunelor a<ENAMEX TYPE="LOCATION">Marii_Britanii</ENAMEX></ENAMEX>.</s>
    <s>" Cota de aur este o cot&abreve; unic&abreve; , dar este cota magic&abreve; . "</s>
    <s>Guvernul<EVENT aspect="NONE" class="OCCURRENCE" eid="e70" eiid="ei2502" eventID="e70" polarity="POS" pos="VERB" tense="PAST">a p&abreve;strat</EVENT>cota unic&abreve;<SIGNAL sid="s71">dup&abreve;</SIGNAL><EVENT aspect="NONE" class="OCCURRENCE" eid="e72" eiid="ei2503" eventID="e72" polarity="POS" pos="NOUN" tense="PRESPART">v&acirc;nzarea</EVENT>cotei sale la<ENAMEX TYPE="ORGANIZATION">Jaguar</ENAMEX><SIGNAL sid="s329">&icirc;n</SIGNAL><TIMEX3 functionInDocument="NONE" temporalFunction="false" tid="t330" type="DATE" value="1984">1984</TIMEX3>-- parte a unei practici na&tcedil;ionaliste de protejare a &icirc;ntreprinderilor de&tcedil;inute de fostul guvern pentru a abate criticile de privatizare .</s>
    <s>Restric&tcedil;ia<NUMEX TYPE="PERCENT">de 15%</NUMEX>acoper&abreve; orice pretendent aspirant , britanic sau str&abreve;in .</s>
    <s><ENAMEX TYPE="ORGANIZATION">Ford</ENAMEX>este<EVENT aspect="NONE" class="I_STATE" eid="e1988" eiid="ei2504" eventID="e1988" polarity="POS" pos="VERB" tense="PRESENT">dispus</EVENT>s&abreve;<EVENT aspect="NONE" class="OCCURRENCE" eid="e82" eiid="ei2505" eventID="e82" polarity="POS" pos="VERB" tense="INFINITIVE">liciteze</EVENT>pentru<NUMEX TYPE="PERCENT">100%</NUMEX>din ac&tcedil;iunile<ENAMEX TYPE="ORGANIZATION">Jaguar</ENAMEX><SIGNAL sid="s2202">dac&abreve;</SIGNAL>at&acirc;t guvernul c&acirc;t &scedil;i ac&tcedil;ionarii<ENAMEX TYPE="ORGANIZATION">Jaguar</ENAMEX><EVENT aspect="NONE" class="I_ACTION" eid="e84" eiid="ei2506" eventID="e84" polarity="POS" pos="NOUN" tense="PRESENT">sunt de acord</EVENT>s&abreve;<EVENT aspect="NONE" class="OCCURRENCE" eid="e86" eiid="ei2507" eventID="e86" polarity="POS" pos="VERB" tense="INFINITIVE">relaxeze</EVENT>prematur bariera anti-preluare .</s>
    <s>Ca principal ac&tcedil;ionar al<ENAMEX TYPE="ORGANIZATION">Jaguar</ENAMEX>&scedil;i cel mai mare fabricant de ma&scedil;ini al<ENAMEX TYPE="LOCATION">Marii_Britanii</ENAMEX>,<ENAMEX TYPE="ORGANIZATION">Ford</ENAMEX>ar putea<EVENT aspect="NONE" class="OCCURRENCE" eid="e87" eiid="ei2508" eventID="e87" modality="could" polarity="POS" pos="NOUN" tense="NONE">pune</EVENT> gaz pe foc<EVENT aspect="NONE" class="I_ACTION" eid="e89" eiid="ei2509" eventID="e89" polarity="POS" pos="VERB" tense="NONE">convoc&acirc;nd</EVENT>o<EVENT aspect="NONE" class="OCCURRENCE" eid="e90" eiid="ei2510" eventID="e90" polarity="POS" pos="NOUN" tense="NONE">&icirc;ntrunire</EVENT>special&abreve; a ac&tcedil;ionarilor &scedil;i<EVENT aspect="NONE" class="I_ACTION" eid="e91" eiid="ei2511" eventID="e91" polarity="POS" pos="VERB" tense="NONE">&icirc;ndemn&acirc;ndu</EVENT>-&scedil;i ac&tcedil;ionarii s&abreve;<EVENT aspect="NONE" class="OCCURRENCE" eid="e1985" eiid="ei2512" eventID="e1985" polarity="POS" pos="VERB" tense="INFINITIVE">coboare</EVENT>limitele devreme .</s>
    <s><ENAMEX TYPE="ORGANIZATION">Ford</ENAMEX>ar putea<EVENT aspect="NONE" class="OCCURRENCE" eid="e92" eiid="ei2513" eventID="e92" modality="might" polarity="POS" pos="VERB" tense="NONE">reu&scedil;i</EVENT>deoarece mul&tcedil;i ac&tcedil;ionari sunt speculan&tcedil;i<EVENT aspect="NONE" class="I_STATE" eid="e1986" eiid="ei2514" eventID="e1986" polarity="POS" pos="ADJECTIVE" tense="PRESENT">dornici</EVENT>de o<EVENT aspect="NONE" class="OCCURRENCE" eid="e94" eiid="ei2515" eventID="e94" polarity="POS" pos="NOUN" tense="NONE">licitare</EVENT>total&abreve; sau investitori institu&tcedil;ionali<EVENT aspect="NONE" class="I_STATE" eid="e1987" eiid="ei2516" eventID="e1987" polarity="POS" pos="VERB" tense="PRESENT">nemul&tcedil;umi&tcedil;i</EVENT>de<EVENT aspect="NONE" class="I_ACTION" eid="e95" eiid="ei2517" eventID="e95" polarity="POS" pos="NOUN" tense="NONE">administrarea</EVENT>conducerii<ENAMEX TYPE="ORGANIZATION">Jaguar</ENAMEX>a<EVENT aspect="NONE" class="STATE" eid="e1994" eiid="ei2518" eventID="e1994" polarity="POS" pos="NOUN" tense="NONE">dificult&abreve;&tcedil;ilor</EVENT>ei financiare<TIMEX3 anchorTimeID="t157" functionInDocument="NONE" temporalFunction="true" tid="t1992" type="DATE" value="PRESENT_REF">curente</TIMEX3>.</s>
    <s>Guvernul nu ar<EVENT aspect="NONE" class="OCCURRENCE" eid="e97" eiid="ei2519" eventID="e97" modality="would" polarity="NEG" pos="VERB" tense="NONE">ceda</EVENT>probabil u&scedil;or unui atac ostil din partea<ENAMEX TYPE="ORGANIZATION">Ford</ENAMEX>, totu&scedil;i .</s>
    <s>A<EVENT aspect="PERFECTIVE" class="OCCURRENCE" eid="e101" eiid="ei2520" eventID="e101" polarity="POS" pos="VERB" tense="PRESENT">renun&tcedil;at</EVENT>la o cot&abreve; de aur doar odat&abreve;<SIGNAL sid="s102">&icirc;nainte</SIGNAL>--<SIGNAL sid="s1996">&icirc;n timpul</SIGNAL><EVENT aspect="NONE" class="OCCURRENCE" eid="e103" eiid="ei2521" eventID="e103" polarity="POS" pos="NOUN" tense="NONE">prelu&abreve;rii</EVENT> de 2 . 5_miliarde ( $ 4 miliarde ) de_c&abreve;tre<ENAMEX TYPE="ORGANIZATION">British Petroleum</ENAMEX>a Britoil PLC <SIGNAL sid="s1997">&icirc;n</SIGNAL> <TIMEX3 functionInDocument="NONE" temporalFunction="false" tid="t1998" type="DATE" value="1988">1988</TIMEX3> .</s>
    <s>Prin<EVENT aspect="NONE" class="OCCURRENCE" eid="e104" eiid="ei2522" eventID="e104" polarity="POS" pos="NOUN" tense="NONE">curtarea</EVENT>legiuitorilor britanici ,<ENAMEX TYPE="ORGANIZATION">GM</ENAMEX>a<EVENT aspect="PERFECTIVE" class="I_ACTION" eid="e105" eiid="ei2523" eventID="e105" polarity="POS" pos="VERB" tense="PRESENT">semnalat</EVENT>c&abreve;<EVENT aspect="NONE" class="I_STATE" eid="e1999" eiid="ei2524" eventID="e1999" polarity="POS" pos="NOUN" tense="NONE">disponibilitatea</EVENT>de a<EVENT aspect="NONE" class="OCCURRENCE" eid="e107" eiid="ei2525" eventID="e107" polarity="POS" pos="VERB" tense="INFINITIVE">se &icirc;nvoi</EVENT>pentru o cot&abreve; minoritar&abreve; ar<EVENT aspect="NONE" class="ASPECTUAL" eid="e109" eiid="ei2526" eventID="e109" modality="would" polarity="POS" pos="VERB" tense="NONE">men&tcedil;ine</EVENT><ENAMEX TYPE="ORGANIZATION">Jaguar</ENAMEX><EVENT aspect="NONE" class="STATE" eid="e2001" eiid="ei2528" eventID="e2001" polarity="POS" pos="ADJECTIVE" tense="NONE">independent</EVENT>&scedil;i ca<EVENT aspect="NONE" class="STATE" eid="e2000" eiid="ei2527" eventID="e2000" polarity="POS" pos="ADJECTIVE" tense="NONE">proprietate britanic&abreve;</EVENT>.</s>
    <s><TIMEX3 anchorTimeID="t157" functionInDocument="NONE" temporalFunction="true" tid="t2007" type="DATE" value="1989-WXX">S&abreve;pt&abreve;m&acirc;na aceasta</TIMEX3>, gigantul auto<ENAMEX TYPE="LOCATION">american</ENAMEX><EVENT aspect="NONE" class="OCCURRENCE" eid="e111" eiid="ei2529" eventID="e111" polarity="POS" pos="VERB" tense="PAST">a pl&abreve;tit</EVENT>pentru_ca<CARDINAL>10</CARDINAL>membri<ENAMEX TYPE="ORGANIZATION">ai Camerei Comunelor</ENAMEX>&scedil;i<CARDINAL>doi</CARDINAL>membri<ENAMEX TYPE="ORGANIZATION">ai Camerei Lorzilor</ENAMEX>s&abreve;<EVENT aspect="NONE" class="OCCURRENCE" eid="e113" eiid="ei2530" eventID="e113" polarity="POS" pos="VERB" tense="INFINITIVE">zboare</EVENT>la<ENAMEX TYPE="LOCATION">Detroit</ENAMEX>&scedil;i s&abreve;-i<EVENT aspect="NONE" class="OCCURRENCE" eid="e114" eiid="ei2531" eventID="e114" polarity="POS" pos="VERB" tense="NONE">viziteze</EVENT>opera&tcedil;iunile de acolo .</s>
    <s>&Icirc;n timp ce<EVENT aspect="NONE" class="OCCURRENCE" eid="e116" eiid="ei2532" eventID="e116" polarity="POS" pos="NOUN" tense="NONE">vizita</EVENT>nu a fost legat&abreve; de<ENAMEX TYPE="ORGANIZATION">Jaguar</ENAMEX>,<ENAMEX TYPE="PERSON">pre&scedil;edintele<ENAMEX TYPE="ORGANIZATION">GM</ENAMEX>Roger Smith</ENAMEX><EVENT aspect="NONE" class="OCCURRENCE" eid="e117" eiid="ei2533" eventID="e117" polarity="POS" pos="VERB" tense="PAST">a r&abreve;spuns</EVENT><TIMEX3 anchorTimeID="t157" functionInDocument="NONE" temporalFunction="true" tid="t2386" type="DATE" value="1989-10-24">joi</TIMEX3><EVENT aspect="NONE" class="OCCURRENCE" eid="e118" eiid="ei2534" eventID="e118" polarity="POS" pos="NOUN" tense="NONE">&icirc;ntreb&abreve;rilor</EVENT>legiuitorilor despre aceasta<SIGNAL sid="s2003">la</SIGNAL><EVENT aspect="NONE" class="OCCURRENCE" eid="e2385" eiid="ei2535" eventID="e2385" polarity="POS" pos="NOUN" tense="NONE">pr&acirc;nz</EVENT>.</s>
    <s>El<EVENT aspect="NONE" class="REPORTING" eid="e119" eiid="ei2536" eventID="e119" polarity="POS" pos="VERB" tense="PAST">a spus</EVENT>c&abreve;<ENAMEX TYPE="ORGANIZATION">Jaguar</ENAMEX>" nu ar trebui s&abreve; fie<EVENT aspect="NONE" class="OCCURRENCE" eid="e120" eiid="ei2537" eventID="e120" modality="should" polarity="NEG" pos="VERB" tense="NONE">sufocat</EVENT>de nimeni altcineva , "<EVENT aspect="NONE" class="REPORTING" eid="e123" eiid="ei2538" eventID="e123" polarity="POS" pos="VERB" tense="PAST">&scedil;i- a amintit</EVENT>un participant .</s>
    <s>Politica influen&tcedil;eaz&abreve; &scedil;i g&acirc;ndirea guvernului asupra restric&tcedil;iei anti-preluare .</s>
    <s>Conservatorii nu &icirc;ndr&abreve;znesc s&abreve; primejduiasc&abreve; locurile<ENAMEX TYPE="PERSON">Tory</ENAMEX>marginale &icirc;n<ENAMEX TYPE="LOCATION">Coventry</ENAMEX>, unde<ENAMEX TYPE="ORGANIZATION">Jaguar</ENAMEX>are sedii , nici nu poate guvernul s&abreve; se retrag&abreve; u&scedil;or de_la protec&tcedil;ia promis&abreve; pentru o companie privatizat&abreve; &icirc;n_timp_ce continu&abreve; planuri controversate de a privatiza majoritatea industriilor de ap&abreve; &scedil;i electricitate ale<ENAMEX TYPE="LOCATION">Marii_Britanii</ENAMEX>.</s>
    <s><ENAMEX TYPE="PERSON">Primul ministru Margaret Thatcher</ENAMEX>ar putea fi totu&scedil;i<EVENT aspect="NONE" class="I_STATE" eid="e2011" eiid="ei2539" eventID="e2011" modality="might" polarity="POS" pos="ADJECTIVE" tense="NONE">receptiv&abreve;</EVENT>la orice<EVENT aspect="NONE" class="I_ACTION" eid="e138" eiid="ei2540" eventID="e138" polarity="POS" pos="NOUN" tense="NONE">solicitare</EVENT>a<ENAMEX TYPE="PERSON">pre&scedil;edintelui<ENAMEX TYPE="ORGANIZATION">Jaguar</ENAMEX>Sir John Egan</ENAMEX>de<EVENT aspect="NONE" class="OCCURRENCE" eid="e139" eiid="ei2541" eventID="e139" polarity="POS" pos="NOUN" tense="NONE">&icirc;ndep&abreve;rtare</EVENT>timpurie a restric&tcedil;iei pentru a<EVENT aspect="NONE" class="I_ACTION" eid="e141" eiid="ei2542" eventID="e141" polarity="POS" pos="VERB" tense="INFINITIVE">l&abreve;sa</EVENT><ENAMEX TYPE="ORGANIZATION">GM</ENAMEX><EVENT aspect="NONE" class="OCCURRENCE" eid="e142" eiid="ei2543" eventID="e142" polarity="POS" pos="VERB" tense="PAST">s&abreve; adune</EVENT>mai mult de<NUMEX TYPE="PERCENT">15%</NUMEX>sau<EVENT aspect="NONE" class="I_ACTION" eid="e143" eiid="ei2544" eventID="e143" polarity="POS" pos="VERB" tense="NONE">s&abreve; aduc&abreve;</EVENT>o<EVENT aspect="NONE" class="OCCURRENCE" eid="e2012" eiid="ei2545" eventID="e2012" polarity="POS" pos="NOUN" tense="NONE">ofert&abreve;</EVENT>prietenoas&abreve; de pretenden&tcedil;&abreve; &icirc;mpotriva<ENAMEX TYPE="ORGANIZATION">Ford</ENAMEX>.</s>
    <s>P&acirc;n&abreve; la urm&abreve; ,<ENAMEX TYPE="PERSON">Sir John</ENAMEX>-- mai_degrab&abreve; dec&acirc;t guvernul sau ac&tcedil;ionarii<ENAMEX TYPE="ORGANIZATION">Jaguar</ENAMEX>-- ar putea de&tcedil;ine cheia care descuie cota de aur .</s>
  </TEXT>
  <TLINK eventID="e2011" lid="l112" relType="AFTER" relatedToTime="t157"/>
  <TLINK eventID="e2001" lid="l111" relType="SIMULTANEOUS" relatedToEvent="e2001"/>
  <TLINK eventID="e2000" lid="l110" relType="IS_INCLUDED" relatedToTime="t157"/>
  <TLINK eventID="e97" lid="l109" relType="AFTER" relatedToTime="t157"/>
  <TLINK eventID="e69" lid="l108" relType="BEFORE" relatedToTime="t157"/>
  <TLINK eventID="e67" lid="l107" relType="IS_INCLUDED" relatedToTime="t157"/>
  <TLINK eventID="e53" lid="l106" relType="BEFORE" relatedToTime="t157"/>
  <TLINK eventID="e50" lid="l105" relType="ENDS" relatedToEvent="e52"/>
  <TLINK eventID="e52" lid="l104" relType="IDENTITY" relatedToEvent="e2091"/>
  <TLINK eventID="e2091" lid="l103" relType="AFTER" relatedToTime="t314"/>
  <TLINK eventID="e2386" lid="l102" relType="IS_INCLUDED" relatedToTime="t313"/>
  <TLINK eventID="e29" lid="l101" relType="IS_INCLUDED" relatedToTime="t157"/>
  <TLINK eventID="e152" lid="l100" relType="IDENTITY" relatedToEvent="e159"/>
  <TLINK eventID="e149" lid="l99" relType="IS_INCLUDED" relatedToTime="t157"/>
  <TLINK eventID="e143" lid="l1" relType="BEGINS" relatedToEvent="e2012"/>
  <TLINK eventID="e1" lid="l2" relType="INCLUDES" relatedToTime="t157"/>
  <TLINK eventID="e1" lid="l3" relType="SIMULTANEOUS" relatedToEvent="e4"/>
  <TLINK eventID="e4" lid="l4" relType="IDENTITY" relatedToEvent="e5"/>
  <TLINK eventID="e5" lid="l5" relType="IS_INCLUDED" relatedToEvent="e6"/>
  <TLINK eventID="e8" lid="l6" relType="IS_INCLUDED" relatedToTime="t158"/>
  <TLINK eventID="e11" lid="l7" relType="IS_INCLUDED" relatedToTime="t161"/>
  <TLINK eventID="e13" lid="l8" relType="AFTER" relatedToEvent="e8"/>
  <TLINK eventID="e16" lid="l9" relType="ENDED_BY" relatedToEvent="e150"/>
  <TLINK eventID="e14" lid="l10" relType="AFTER" relatedToEvent="e17" signalID="s151"/>
  <TLINK eventID="e20" lid="l11" relType="BEFORE" relatedToTime="t157"/>
  <TLINK eventID="e154" lid="l12" relType="INCLUDES" relatedToEvent="e1"/>
  <TLINK eventID="e154" lid="l13" relType="AFTER" relatedToEvent="e22" signalID="s155"/>
  <TLINK eventID="e22" lid="l14" relType="IS_INCLUDED" relatedToTime="t164"/>
  <TLINK eventID="e35" lid="l15" relType="INCLUDES" relatedToEvent="e38"/>
  <TLINK eventID="e38" lid="l16" relType="BEFORE" relatedToTime="t157"/>
  <TLINK eventID="e38" lid="l17" relType="IS_INCLUDED" relatedToEvent="e39"/>
  <TLINK eventID="e39" lid="l18" relType="IS_INCLUDED" relatedToTime="t313"/>
  <TLINK lid="l19" relType="BEGINS" relatedToEvent="e42" timeID="t314"/>
  <TLINK eventID="e48" lid="l20" relType="IS_INCLUDED" relatedToEvent="e316"/>
  <TLINK eventID="e316" lid="l21" relType="IS_INCLUDED" relatedToTime="t315"/>
  <TLINK eventID="e316" lid="l22" relType="BEFORE" relatedToTime="t157"/>
  <TLINK eventID="e30" lid="l23" relType="INCLUDES" relatedToEvent="e2073"/>
  <TLINK eventID="e318" lid="l24" relType="BEFORE" relatedToEvent="e56"/>
  <TLINK eventID="e59" lid="l25" relType="ENDED_BY" relatedToEvent="e63" signalID="s62"/>
  <TLINK eventID="e63" lid="l26" relType="ENDS" relatedToEvent="e322"/>
  <TLINK eventID="e63" lid="l27" relType="IS_INCLUDED" relatedToTime="t325" signalID="s326"/>
  <TLINK eventID="e66" lid="l28" relType="IS_INCLUDED" relatedToTime="t327" signalID="s328"/>
  <TLINK eventID="e70" lid="l29" relType="AFTER" relatedToEvent="e72" signalID="s71"/>
  <TLINK eventID="e72" lid="l30" relType="IS_INCLUDED" relatedToTime="t330" signalID="s329"/>
  <TLINK eventID="e1988" lid="l31" relType="INCLUDES" relatedToTime="t157"/>
  <TLINK eventID="e84" lid="l32" relType="BEFORE" relatedToEvent="e82"/>
  <TLINK eventID="e87" lid="l33" relType="AFTER" relatedToEvent="e89"/>
  <TLINK eventID="e87" lid="l34" relType="AFTER" relatedToEvent="e91"/>
  <TLINK eventID="e91" lid="l35" relType="IS_INCLUDED" relatedToEvent="e90"/>
  <TLINK eventID="e1986" lid="l37" relType="BEFORE" relatedToEvent="e92"/>
  <TLINK eventID="e1986" lid="l38" relType="INCLUDES" relatedToTime="t157"/>
  <TLINK eventID="e1986" lid="l39" relType="SIMULTANEOUS" relatedToEvent="e1987"/>
  <TLINK lid="l40" relType="INCLUDES" relatedToEvent="e1994" timeID="t1992"/>
  <TLINK eventID="e101" lid="l41" relType="BEFORE" relatedToTime="t157" signalID="s102"/>
  <TLINK eventID="e101" lid="l42" relType="IS_INCLUDED" relatedToEvent="e103" signalID="s1996"/>
  <TLINK eventID="e103" lid="l43" relType="IS_INCLUDED" relatedToTime="t1998" signalID="s1997"/>
  <TLINK eventID="e104" lid="l44" relType="SIMULTANEOUS" relatedToEvent="e105"/>
  <TLINK eventID="e1999" lid="l45" relType="BEFORE" relatedToEvent="e109"/>
  <TLINK lid="l46" relType="IS_INCLUDED" relatedToEvent="e111" timeID="t2007"/>
  <TLINK eventID="e116" lid="l47" relType="INCLUDES" relatedToEvent="e113"/>
  <TLINK eventID="e116" lid="l48" relType="INCLUDES" relatedToEvent="e114"/>
  <TLINK eventID="e116" lid="l49" relType="BEFORE" relatedToTime="t157"/>
  <TLINK eventID="e117" lid="l50" relType="AFTER" relatedToEvent="e118"/>
  <TLINK eventID="e118" lid="l51" relType="AFTER" relatedToEvent="e116"/>
  <TLINK eventID="e117" lid="l52" relType="IS_INCLUDED" relatedToEvent="e2385" signalID="s2003"/>
  <TLINK eventID="e2385" lid="l53" relType="IS_INCLUDED" relatedToTime="t2386"/>
  <TLINK eventID="e119" lid="l54" relType="IS_INCLUDED" relatedToEvent="e117"/>
  <TLINK eventID="e123" lid="l55" relType="AFTER" relatedToEvent="e117"/>
  <SLINK eventID="e117" lid="l98" relType="FACTIVE" subordinatedEvent="e118"/>
  <SLINK eventID="e84" lid="l56" relType="CONDITIONAL" signalID="s2202" subordinatedEvent="e82"/>
  <SLINK eventID="e1" lid="l57" relType="MODAL" subordinatedEvent="e3"/>
  <SLINK eventID="e6" lid="l58" relType="MODAL" subordinatedEvent="e147"/>
  <SLINK eventID="e8" lid="l59" relType="MODAL" subordinatedEvent="e159"/>
  <SLINK eventID="e159" lid="l60" relType="MODAL" subordinatedEvent="e10"/>
  <SLINK eventID="e149" lid="l61" relType="EVIDENTIAL" subordinatedEvent="e8"/>
  <SLINK eventID="e149" lid="l62" relType="EVIDENTIAL" subordinatedEvent="e11"/>
  <SLINK eventID="e13" lid="l63" relType="EVIDENTIAL" subordinatedEvent="e14"/>
  <SLINK eventID="e14" lid="l64" relType="MODAL" subordinatedEvent="e16"/>
  <SLINK eventID="e152" lid="l65" relType="MODAL" subordinatedEvent="e19"/>
  <SLINK eventID="e20" lid="l66" relType="EVIDENTIAL" subordinatedEvent="e13"/>
  <SLINK eventID="e22" lid="l67" relType="EVIDENTIAL" subordinatedEvent="e25"/>
  <SLINK eventID="e25" lid="l68" relType="MODAL" subordinatedEvent="e27"/>
  <SLINK eventID="e35" lid="l69" relType="MODAL" subordinatedEvent="e36"/>
  <SLINK eventID="e48" lid="l70" relType="EVIDENTIAL" subordinatedEvent="e46"/>
  <SLINK eventID="e2073" lid="l71" relType="FACTIVE" subordinatedEvent="e2075"/>
  <SLINK eventID="e56" lid="l72" relType="MODAL" subordinatedEvent="e59"/>
  <SLINK eventID="e64" lid="l73" relType="EVIDENTIAL" subordinatedEvent="e66"/>
  <SLINK eventID="e67" lid="l74" relType="MODAL" subordinatedEvent="e66"/>
  <SLINK eventID="e69" lid="l75" relType="EVIDENTIAL" subordinatedEvent="e64"/>
  <SLINK eventID="e1988" lid="l76" relType="MODAL" subordinatedEvent="e82"/>
  <SLINK eventID="e84" lid="l77" relType="MODAL" subordinatedEvent="e86"/>
  <SLINK eventID="e89" lid="l78" relType="MODAL" subordinatedEvent="e90"/>
  <SLINK eventID="e91" lid="l79" relType="MODAL" subordinatedEvent="e1985"/>
  <SLINK eventID="e1986" lid="l80" relType="MODAL" subordinatedEvent="e94"/>
  <SLINK eventID="e1987" lid="l81" relType="FACTIVE" subordinatedEvent="e95"/>
  <SLINK eventID="e95" lid="l82" relType="FACTIVE" subordinatedEvent="e1994"/>
  <SLINK eventID="e105" lid="l83" relType="MODAL" subordinatedEvent="e109"/>
  <SLINK eventID="e1999" lid="l84" relType="MODAL" subordinatedEvent="e107"/>
  <SLINK eventID="e111" lid="l85" relType="MODAL" subordinatedEvent="e113"/>
  <SLINK eventID="e111" lid="l86" relType="MODAL" subordinatedEvent="e114"/>
  <SLINK eventID="e119" lid="l87" relType="EVIDENTIAL" subordinatedEvent="e120"/>
  <SLINK eventID="e123" lid="l88" relType="EVIDENTIAL" subordinatedEvent="e119"/>
  <SLINK eventID="e2011" lid="l89" relType="FACTIVE" subordinatedEvent="e138"/>
  <SLINK eventID="e138" lid="l90" relType="MODAL" subordinatedEvent="e139"/>
  <SLINK eventID="e139" lid="l91" relType="MODAL" subordinatedEvent="e141"/>
  <SLINK eventID="e141" lid="l92" relType="MODAL" subordinatedEvent="e142"/>
  <SLINK eventID="e141" lid="l93" relType="MODAL" subordinatedEvent="e143"/>
  <ALINK eventID="e29" lid="l94" relType="CULMINATES" relatedToEvent="e30"/>
  <ALINK eventID="e50" lid="l95" relType="TERMINATES" relatedToEvent="e52"/>
  <ALINK eventID="e109" lid="l96" relType="CONTINUES" relatedToEvent="e2000"/>
  <ALINK eventID="e109" lid="l97" relType="CONTINUES" relatedToEvent="e2001"/>
</TimeML>
