<?xml version="1.0" encoding="us-ascii" standalone="no"?>
<!DOCTYPE TimeML SYSTEM "../../dtd/ISO-TimeML-Ro.dtd">
<TimeML xmlns:xsi="http://www.w3.org/2001/XMLSchema-instance" xsi:noNamespaceSchemaLocation="../../dtd/timeml_1.2.1.xsd">
  <DOCNO> WSJ891030-0181 </DOCNO>
  <DD> = 891030 </DD>
  <AN> 891030-0181. </AN>
  <HL> Dutch Firm Seeks
@  To Buy Up to 25%
@  Of Nashua's Stock
@  ----
@  By Lawrence Ingrassia
@  Staff Reporter of The Wall Street Journal </HL>
  <DD> <TIMEX3 functionInDocument="CREATION_TIME" temporalFunction="false" tid="t76" type="DATE" value="1989-10-30">10/30/89</TIMEX3> </DD>
  <SO> WALL STREET JOURNAL (J) </SO>
  <CO> NSH </CO>
  <IN> TENDER OFFERS, MERGERS, ACQUISITIONS (TNM)
BUYBACKS, REDEMPTIONS, SWAP OFFERS (BBK) </IN>
  <DATELINE> NASHUA, N.H.  </DATELINE>
  <TEXT><s><ENAMEX TYPE="ORGANIZATION">Nashua Corp .</ENAMEX>,<EVENT aspect="NONE" class="STATE" eid="e1" eiid="ei1990" eventID="e1" polarity="POS" pos="VERB" tense="PASTPART">zvonit&abreve;</EVENT><SIGNAL sid="s75">pentru</SIGNAL><TIMEX3 functionInDocument="NONE" temporalFunction="false" tid="t77" type="DURATION" value="P6M"><CARDINAL>&scedil;ase</CARDINAL>luni</TIMEX3>ca &tcedil;int&abreve; de preluare poten&tcedil;ial&abreve; ,<EVENT aspect="NONE" class="REPORTING" eid="e3" eiid="ei1991" eventID="e3" polarity="POS" pos="VERB" tense="PAST">a spus</EVENT>c&abreve; o companie olandez&abreve; a<EVENT aspect="PERFECTIVE" class="I_ACTION" eid="e4" eiid="ei1992" eventID="e4" polarity="POS" pos="VERB" tense="PRESENT">umblat</EVENT><EVENT aspect="NONE" class="I_STATE" eid="e5" eiid="ei1993" eventID="e5" polarity="POS" pos="NOUN" tense="NONE">dup&abreve; aprobarea</EVENT>SUA s&abreve;<EVENT aspect="NONE" class="OCCURRENCE" eid="e7" eiid="ei1994" eventID="e7" polarity="POS" pos="VERB" tense="INFINITIVE">cumpere</EVENT>p&acirc;n&abreve;_la<NUMEX TYPE="PERCENT">25%</NUMEX>din ac&tcedil;iunile<ENAMEX TYPE="LOCATION">Nashua</ENAMEX>.</s>
  <s><ENAMEX TYPE="LOCATION">Nashua</ENAMEX><EVENT aspect="NONE" class="OCCURRENCE" eid="e8" eiid="ei1995" eventID="e8" polarity="POS" pos="VERB" tense="PAST">a replicat</EVENT><SIGNAL sid="s78">imediat</SIGNAL><EVENT aspect="NONE" class="OCCURRENCE" eid="e9" eiid="ei1996" eventID="e9" polarity="POS" pos="VERB" tense="PRESPART">&icirc;nt&abreve;rind</EVENT>un plan de prescriere &scedil;i<EVENT aspect="NONE" class="REPORTING" eid="e10" eiid="ei1997" eventID="e10" polarity="POS" pos="VERB" tense="PRESPART">spun&acirc;nd</EVENT>c&abreve; va<EVENT aspect="NONE" class="OCCURRENCE" eid="e11" eiid="ei1998" eventID="e11" polarity="POS" pos="VERB" tense="FUTURE">r&abreve;scump&abreve;ra</EVENT>p&acirc;n&abreve;_la<CARDINAL>un_milion</CARDINAL>din ac&tcedil;iunile sale sau<NUMEX TYPE="PERCENT">10 , 4%</NUMEX>din cele<CARDINAL>9 , 6_milioane</CARDINAL>importante .</s>
  <s><ENAMEX TYPE="LOCATION">Nashua</ENAMEX>, a c&abreve;rui afacere principal&abreve; este v&acirc;nzarea de copiatoare , ma&scedil;ini de fax &scedil;i consumabile corelate ,<EVENT aspect="NONE" class="REPORTING" eid="e15" eiid="ei1999" eventID="e15" polarity="POS" pos="VERB" tense="PAST">a spus</EVENT>c&abreve;<ENAMEX TYPE="ORGANIZATION">Reiss amp Co. B. V .</ENAMEX>din<ENAMEX TYPE="LOCATION">Olanda</ENAMEX><EVENT aspect="NONE" class="OCCURRENCE" eid="e16" eiid="ei2000" eventID="e16" polarity="POS" pos="VERB" tense="PAST">a completat</EVENT>o<EVENT aspect="NONE" class="I_ACTION" eid="e17" eiid="ei2001" eventID="e17" polarity="POS" pos="NOUN" tense="NONE">cerere</EVENT>la<ENAMEX TYPE="ORGANIZATION">Comisia de comer&tcedil; federal</ENAMEX>sub legea Hart-Scott-Rodino pentru<EVENT aspect="NONE" class="I_STATE" eid="e18" eiid="ei2002" eventID="e18" polarity="POS" pos="NOUN" tense="NONE">permisiunea</EVENT>de a<EVENT aspect="NONE" class="OCCURRENCE" eid="e20" eiid="ei2003" eventID="e20" polarity="POS" pos="VERB" tense="INFINITIVE">cump&abreve;ra</EVENT>mai mult de<NUMEX TYPE="MONEY">$ 15 milioane</NUMEX>din ac&tcedil;iunile<ENAMEX TYPE="LOCATION">Nashua</ENAMEX>dar mai pu&tcedil;in de<NUMEX TYPE="PERCENT">25%</NUMEX>.</s>
  <s><SIGNAL sid="s79">&Icirc;nainte</SIGNAL>, un afiliat al<ENAMEX TYPE="ORGANIZATION">Unicorp Canada</ENAMEX><EVENT aspect="NONE" class="OCCURRENCE" eid="e21" eiid="ei2004" eventID="e21" polarity="POS" pos="VERB" tense="PAST">a relevat</EVENT>fonduri de mai pu&tcedil;in de<NUMEX TYPE="PERCENT">5%</NUMEX>&icirc;n<ENAMEX TYPE="LOCATION">Nashua</ENAMEX>,<EVENT aspect="NONE" class="REPORTING" eid="e80" eiid="ei2005" eventID="e80" polarity="POS" pos="PREPOSITION" tense="PRESPART">conform</EVENT><ENAMEX TYPE="PERSON">economistului</ENAMEX>Daniel<ENAMEX TYPE="PERSON">M. Junius de_la<ENAMEX TYPE="LOCATION">Nashua</ENAMEX></ENAMEX>.</s>
  <s>Fondurile<ENAMEX TYPE="LOCATION">Nashua</ENAMEX>au<EVENT aspect="PERFECTIVE" class="OCCURRENCE" eid="e23" eiid="ei2006" eventID="e23" polarity="POS" pos="VERB" tense="PRESENT">fluctuat</EVENT>brusc la specularea de preluare ,<EVENT aspect="NONE" class="OCCURRENCE" eid="e26" eiid="ei2007" eventID="e26" polarity="POS" pos="VERB" tense="PRESPART">ajung&acirc;nd</EVENT>la un v&acirc;rf<SIGNAL sid="s87">pentru</SIGNAL><TIMEX3 anchorTimeID="t76" functionInDocument="NONE" temporalFunction="true" tid="t88" type="DATE" value="1989">acest an</TIMEX3> de<EVENT aspect="NONE" class="STATE" eid="e268" eiid="ei2039" eventID="e268" polarity="POS" pos="OTHER" tense="NONE">$ 42 . 875</EVENT>o ac&tcedil;iune &icirc;n<TIMEX3 anchorTimeID="t76" functionInDocument="NONE" temporalFunction="true" tid="t89" type="DATE" value="1989-06">iunie</TIMEX3><SIGNAL sid="s84">de_la</SIGNAL><EVENT aspect="NONE" class="STATE" eid="e82" eiid="ei2009" eventID="e82" polarity="POS" pos="NOUN" tense="NONE"><NUMEX TYPE="MONEY">$ 29 . 75</NUMEX></EVENT><SIGNAL sid="s86">&icirc;n</SIGNAL><TIMEX3 anchorTimeID="t76" functionInDocument="NONE" temporalFunction="true" tid="t90" type="DATE" value="1989-03">martie</TIMEX3>.</s>
   <s>Dar compania<EVENT aspect="PERFECTIVE" class="STATE" eid="e91" eiid="ei2010" eventID="e91" polarity="POS" pos="VERB" tense="PRESENT">avusese</EVENT><EVENT aspect="NONE" class="OCCURRENCE" eid="e27" eiid="ei2011" eventID="e27" polarity="POS" pos="NOUN" tense="NONE">rezultate</EVENT>slabe p&acirc;n&abreve; acum<TIMEX3 anchorTimeID="t76" functionInDocument="NONE" temporalFunction="true" tid="t92" type="DATE" value="1989-10-30">anul acesta</TIMEX3>, cu<EVENT aspect="NONE" class="STATE" eid="e249" eiid="ei2012" eventID="e249" polarity="POS" pos="NOUN" tense="NONE">c&acirc;&scedil;tiguri</EVENT><EVENT aspect="NONE" class="OCCURRENCE" eid="e28" eiid="ei2013" eventID="e28" polarity="POS" pos="VERB" tense="PRESPART">sc&abreve;z&acirc;nd</EVENT><NUMEX TYPE="PERCENT">cu 43%</NUMEX>la<NUMEX TYPE="MONEY"><EVENT aspect="NONE" class="STATE" eid="e270" eiid="ei2041" eventID="e270" polarity="POS" pos="OTHER" tense="NONE">$ 13 . 7_milioane</EVENT></NUMEX>, sau<NUMEX TYPE="MONEY">$ 1 . 43</NUMEX>pe ac&tcedil;iune , cu o sc&abreve;dere<NUMEX TYPE="PERCENT">de 4%</NUMEX>a<EVENT aspect="NONE" class="STATE" eid="e266" eiid="ei2015" eventID="e266" polarity="POS" pos="NOUN" tense="NONE">beneficiului</EVENT>la<NUMEX TYPE="MONEY"><EVENT aspect="NONE" class="STATE" eid="e269" eiid="ei2040" eventID="e269" polarity="POS" pos="OTHER" tense="NONE">$ 713 . 5_milioane</EVENT></NUMEX><SIGNAL sid="s97">pe parcursul</SIGNAL><TIMEX3 functionInDocument="NONE" temporalFunction="false" tid="t100" type="DURATION" value="P9M">primelor<CARDINAL>nou&abreve;</CARDINAL>luni</TIMEX3>ale<TIMEX3 anchorTimeID="t76" temporalFunction="true" tid="t1000" type="DATE" value="1989">anului</TIMEX3>.</s>.

<s>Fondurile sale s-au<EVENT aspect="PERFECTIVE" class="OCCURRENCE" eid="e30" eiid="ei2017" eventID="e30" polarity="POS" pos="VERB" tense="PAST">pr&abreve;bu&scedil;it</EVENT><TIMEX3 anchorTimeID="t76" functionInDocument="NONE" temporalFunction="true" tid="t101" type="DATE" value="PAST_REF">recent</TIMEX3>,<EVENT aspect="NONE" class="OCCURRENCE" eid="e31" eiid="ei2018" eventID="e31" polarity="POS" pos="OTHER" tense="PRESPART">&icirc;nchiz&acirc;ndu -se</EVENT>nemodificate<TIMEX3 anchorTimeID="t76" functionInDocument="NONE" temporalFunction="true" tid="t103" type="DATE" value="1989-10-27">vineri</TIMEX3>la<NUMEX TYPE="MONEY">$ 29</NUMEX>ac&tcedil;iunea &icirc;n comer&tcedil; compozit pe<ENAMEX TYPE="ORGANIZATION">pia&tcedil;a de schimb a ac&tcedil;iunilor din New_York</ENAMEX>; la acel pre&tcedil; , compania are o valoare de pia&tcedil;&abreve; + AWMBAw - de aproximativ<NUMEX TYPE="MONEY">$ 278 . 4_milioane</NUMEX>.</s>
<s><ENAMEX TYPE="LOCATION">Nashua</ENAMEX><EVENT aspect="NONE" class="I_ACTION" eid="e35" eiid="ei2020" eventID="e35" polarity="POS" pos="VERB" tense="PAST">a anun&tcedil;at</EVENT><EVENT aspect="NONE" class="OCCURRENCE" eid="e104" eiid="ei2021" eventID="e104" polarity="POS" pos="NOUN" tense="NONE">cererea</EVENT><ENAMEX TYPE="ORGANIZATION">Reiss</ENAMEX><SIGNAL sid="s37">dup&abreve;_ce</SIGNAL><EVENT aspect="NONE" class="STATE" eid="e105" eiid="ei2022" eventID="e105" polarity="POS" pos="NOUN" tense="NONE">pia&tcedil;a</EVENT><EVENT aspect="NONE" class="ASPECTUAL" eid="e38" eiid="ei2023" eventID="e38" polarity="POS" pos="VERB" tense="PAST">s- a &icirc;nchis</EVENT>.</s>
<s><ENAMEX TYPE="PERSON">Dl . Junius</ENAMEX><EVENT aspect="NONE" class="REPORTING" eid="e39" eiid="ei2024" eventID="e39" polarity="POS" pos="VERB" tense="PAST">a spus</EVENT>c&abreve; "<EVENT aspect="NONE" class="I_STATE" eid="e106" eiid="ei2025" eventID="e106" polarity="POS" pos="NOUN" tense="NONE">inten&tcedil;ia</EVENT><ENAMEX TYPE="LOCATION">Nashua</ENAMEX>este de a<EVENT aspect="NONE" class="STATE" eid="e41" eiid="ei2026" eventID="e41" polarity="POS" pos="VERB" tense="INFINITIVE">r&abreve;m&acirc;ne</EVENT>o companie public&abreve; independent&abreve; . "</s>
<s>Compania<EVENT aspect="NONE" class="REPORTING" eid="e42" eiid="ei2027" eventID="e42" polarity="POS" pos="VERB" tense="PAST">a spus</EVENT>c&abreve;<EVENT aspect="NONE" class="OCCURRENCE" eid="e43" eiid="ei2028" eventID="e43" polarity="POS" pos="VERB" tense="PAST">a amendat</EVENT>planul drepturilor ac&tcedil;ionarilor prin<EVENT aspect="NONE" class="OCCURRENCE" eid="e45" eiid="ei2029" eventID="e45" polarity="POS" pos="NOUN" tense="PRESPART">reducerea</EVENT>la<NUMEX TYPE="PERCENT">10%</NUMEX>de_la<NUMEX TYPE="PERCENT">20%</NUMEX>pentru nivelul de proprietate a unui extern care ar activa emiterea c&abreve;tre al&tcedil;i proprietari de drepturi s&abreve; cumpere ac&tcedil;iuni adi&tcedil;ionale ale<ENAMEX TYPE="LOCATION">Nashua</ENAMEX>la jum&abreve;tate de pre&tcedil; ,</s>
<s>&Icirc;n plus , consiliul companiei<EVENT aspect="NONE" class="I_ACTION" eid="e53" eiid="ei2030" eventID="e53" polarity="POS" pos="VERB" tense="PAST">a autorizat</EVENT><EVENT aspect="NONE" class="OCCURRENCE" eid="e54" eiid="ei2031" eventID="e54" polarity="POS" pos="NOUN" tense="NONE">cump&abreve;rarea</EVENT>a p&acirc;n&abreve;_la<CARDINAL>un_milion</CARDINAL>de ac&tcedil;iuni adi&tcedil;ionale .</s>
<s>Sub un<EVENT aspect="NONE" class="STATE" eid="e107" eiid="ei2032" eventID="e107" polarity="POS" pos="NOUN" tense="NONE">program</EVENT><EVENT aspect="NONE" class="I_ACTION" eid="e56" eiid="ei2033" eventID="e56" polarity="POS" pos="VERB" tense="PASTPART">aprobat</EVENT>de companie<SIGNAL sid="s108">&icirc;n</SIGNAL><TIMEX3 functionInDocument="NONE" temporalFunction="false" tid="t109" type="DATE" value="1987">1987</TIMEX3>care nu a specificat valoarea unei ac&tcedil;iuni ,<ENAMEX TYPE="LOCATION">Nashua</ENAMEX>a<EVENT aspect="PERFECTIVE" class="OCCURRENCE" eid="e59" eiid="ei2034" eventID="e59" polarity="POS" pos="VERB" tense="PAST">achizi&tcedil;ionat</EVENT><CARDINAL>481.000</CARDINAL>ac&tcedil;iuni<SIGNAL sid="s110">p&acirc;n&abreve;_&icirc;n</SIGNAL><TIMEX3 anchorTimeID="t76" functionInDocument="NONE" temporalFunction="true" tid="t111" type="DATE" value="1989-09-29">29_septembrie</TIMEX3>.</s>
<s><ENAMEX TYPE="PERSON">Alex Henderson , un analist la<ENAMEX TYPE="ORGANIZATION">Prudential-Bache Securities</ENAMEX></ENAMEX>,<EVENT aspect="NONE" class="REPORTING" eid="e60" eiid="ei2035" eventID="e60" polarity="POS" pos="VERB" tense="PAST">a spus</EVENT>c&abreve; &icirc;n_timp_ce performan&tcedil;a<ENAMEX TYPE="LOCATION">Nashua</ENAMEX><TIMEX3 anchorTimeID="t76" functionInDocument="NONE" temporalFunction="true" tid="t112" type="DATE" value="1989">acest an</TIMEX3>a fost "<EVENT aspect="PERFECTIVE" class="STATE" eid="e113" eiid="ei2036" eventID="e113" polarity="POS" pos="ADJECTIVE" tense="PRESENT">atroce</EVENT>, " compania este totu&scedil;i atractiv&abreve; ca un " candidat de &icirc;nchidere clasic pentru_c&abreve; nu este nici o similaritate &icirc;ntre afacerile ei {<CARDINAL>patru</CARDINAL>} "</s>
<s>El<EVENT aspect="NONE" class="I_ACTION" eid="e65" eiid="ei2037" eventID="e65" polarity="POS" pos="VERB" tense="PAST">a estimat</EVENT><EVENT aspect="NONE" class="STATE" eid="e114" eiid="ei2038" eventID="e114" polarity="POS" pos="NOUN" tense="NONE">valoarea</EVENT>de &icirc;nchidere la<NUMEX TYPE="MONEY">$ 55</NUMEX>ac&tcedil;iunea .</s>
<s>Pe l&acirc;ng&abreve; v&acirc;nzarea de fotocopiatoare &scedil;i faxuri de fabrica&tcedil;ie japonez&abreve; &icirc;n<ENAMEX TYPE="LOCATION">Europa</ENAMEX>&scedil;i consumabile de copiator &icirc;n<ENAMEX TYPE="LOCATION">SUA</ENAMEX>,<ENAMEX TYPE="LOCATION">Nashua</ENAMEX>are alte<CARDINAL>trei</CARDINAL>afaceri majore : etichete &scedil;i benzi , discuri de stocare a datelor pentru computere &scedil;i fotofini&scedil; po&scedil;t&abreve; .</s>
</TEXT>
  <TLINK eventID="e114" lid="l57" relType="AFTER" relatedToTime="t76"/>
  <TLINK eventID="e53" lid="l56" relType="BEFORE" relatedToTime="t76"/>
  <TLINK eventID="e105" lid="l55" relType="BEFORE" relatedToEvent="e35"/>
  <TLINK eventID="e270" lid="l54" relType="AFTER" relatedToEvent="e28"/>
  <TLINK eventID="e28" lid="l53" relType="IS_INCLUDED" relatedToTime="t92"/>
  <TLINK eventID="e269" lid="l52" relType="AFTER" relatedToEvent="e28"/>
  <TLINK eventID="e268" lid="l51" relType="AFTER" relatedToEvent="e26"/>
  <TLINK eventID="e80" lid="l50" relType="IS_INCLUDED" relatedToTime="t76"/>
  <TLINK lid="l1" relType="BEGINS" relatedToTime="t1000" timeID="t100"/>
  <TLINK eventID="e3" lid="l2" relType="BEFORE" relatedToTime="t76"/>
  <TLINK eventID="e1" lid="l3" relType="BEFORE" relatedToTime="t76"/>
  <TLINK eventID="e1" lid="l4" relType="DURING" relatedToTime="t77" signalID="s75"/>
  <TLINK eventID="e8" lid="l5" relType="IAFTER" relatedToEvent="e3" signalID="s78"/>
  <TLINK eventID="e8" lid="l6" relType="IDENTITY" relatedToEvent="e9"/>
  <TLINK eventID="e8" lid="l7" relType="IDENTITY" relatedToEvent="e10"/>
  <TLINK eventID="e15" lid="l8" relType="IDENTITY" relatedToEvent="e10"/>
  <TLINK eventID="e21" lid="l9" relType="BEFORE" relatedToEvent="e16" signalID="s79"/>
  <TLINK eventID="e23" lid="l10" relType="BEFORE" relatedToTime="t76"/>
  <TLINK eventID="e23" lid="l11" relType="INCLUDES" relatedToEvent="e26"/>
  <TLINK eventID="e26" lid="l12" relType="BEGUN_BY" relatedToEvent="e82" signalID="s84"/>
  <TLINK eventID="e82" lid="l13" relType="IS_INCLUDED" relatedToTime="t90" signalID="s86"/>
    <TLINK eventID="e26" lid="l14" relType="DURING" relatedToTime="t88" signalID="s87"/>
  <TLINK eventID="e91" lid="l15" relType="BEFORE" relatedToTime="t76"/>
  <TLINK eventID="e91" lid="l16" relType="IDENTITY" relatedToEvent="e27"/>
  <TLINK eventID="e91" lid="l17" relType="DURING" relatedToTime="t92"/>
  <TLINK eventID="e249" lid="l18" relType="DURING" relatedToTime="t92"/>
  <TLINK eventID="e266" lid="l19" relType="DURING" relatedToTime="t100" signalID="s97"/>
  <TLINK eventID="e30" lid="l20" relType="IS_INCLUDED" relatedToTime="t101"/>
  <TLINK eventID="e30" lid="l21" relType="ENDED_BY" relatedToEvent="e31"/>
  <TLINK eventID="e31" lid="l22" relType="IS_INCLUDED" relatedToTime="t103"/>
  <TLINK eventID="e35" lid="l23" relType="IS_INCLUDED" relatedToTime="t76"/>
  <TLINK eventID="e35" lid="l24" relType="AFTER" relatedToEvent="e38" signalID="s37"/>
  <TLINK eventID="e42" lid="l25" relType="IDENTITY" relatedToEvent="e39"/>
  <TLINK eventID="e43" lid="l26" relType="AFTER" relatedToEvent="e45"/>
  <TLINK eventID="e56" lid="l27" relType="IS_INCLUDED" relatedToTime="t109" signalID="s108"/>
  <TLINK eventID="e59" lid="l28" relType="IS_INCLUDED" relatedToEvent="e107"/>
  <TLINK eventID="e59" lid="l29" relType="ENDED_BY" relatedToTime="t111" signalID="s110"/>
  <TLINK eventID="e113" lid="l30" relType="IS_INCLUDED" relatedToTime="t112"/>
  <TLINK eventID="e65" lid="l31" relType="IS_INCLUDED" relatedToEvent="e60"/>
  <SLINK eventID="e65" lid="l49" relType="MODAL" subordinatedEvent="e114"/>
  <SLINK eventID="e3" lid="l32" relType="EVIDENTIAL" subordinatedEvent="e4"/>
  <SLINK eventID="e4" lid="l33" relType="MODAL" subordinatedEvent="e5"/>
  <SLINK eventID="e5" lid="l34" relType="MODAL" subordinatedEvent="e7"/>
  <SLINK eventID="e10" lid="l35" relType="EVIDENTIAL" subordinatedEvent="e11"/>
  <SLINK eventID="e15" lid="l36" relType="EVIDENTIAL" subordinatedEvent="e16"/>
  <SLINK eventID="e16" lid="l37" relType="FACTIVE" subordinatedEvent="e17"/>
  <SLINK eventID="e17" lid="l38" relType="MODAL" subordinatedEvent="e18"/>
  <SLINK eventID="e18" lid="l39" relType="MODAL" subordinatedEvent="e20"/>
  <SLINK eventID="e80" lid="l40" relType="EVIDENTIAL" subordinatedEvent="e21"/>
  <SLINK eventID="e35" lid="l41" relType="EVIDENTIAL" subordinatedEvent="e104"/>
  <SLINK eventID="e39" lid="l42" relType="EVIDENTIAL" subordinatedEvent="e106"/>
  <SLINK eventID="e106" lid="l43" relType="MODAL" subordinatedEvent="e41"/>
  <SLINK eventID="e42" lid="l44" relType="EVIDENTIAL" subordinatedEvent="e43"/>
  <SLINK eventID="e53" lid="l45" relType="MODAL" subordinatedEvent="e54"/>
  <SLINK eventID="e56" lid="l46" relType="FACTIVE" subordinatedEvent="e107"/>
  <SLINK eventID="e60" lid="l47" relType="EVIDENTIAL" subordinatedEvent="e113"/>
  <ALINK eventID="e38" lid="l48" relType="TERMINATES" relatedToEvent="e105"/>
</TimeML>
